README
setup.py
windyLib.py
windyLib.egg-info/PKG-INFO
windyLib.egg-info/SOURCES.txt
windyLib.egg-info/dependency_links.txt
windyLib.egg-info/top_level.txt