Metadata-Version: 1.0
Name: windyLib
Version: 0.1.4
Summary: weather data access and analysis from www.windy.com
Home-page: https://github.com/Louis-He/windyLib
Author: Louis He
Author-email: 1726110778@qq.com
License: UNKNOWN
Platform: UNKNOWN
